rest_friendship/__init__.py
rest_friendship/apps.py
rest_friendship/serializers.py
rest_friendship/urls.py
rest_friendship/views.py
tests/__init__.py
tests/conftest.py
tests/factories.py
tests/models.py
tests/serializers.py
tests/test_views.py
tests/urls.py
django_rest_friendship-0.2.1.dist-info/LICENSE
django_rest_friendship-0.2.1.dist-info/METADATA
django_rest_friendship-0.2.1.dist-info/WHEEL
django_rest_friendship-0.2.1.dist-info/top_level.txt
django_rest_friendship-0.2.1.dist-info/RECORD
