Metadata-Version: 2.1
Name: django-rest-friendship
Version: 0.2.1
Summary: DRF endpoints for django-friendship
Home-page: https://github.com/dnmellen/django-rest-friendship
Author: Diego Navarro Mellén
Author-email: dnmellen@gmail.com
License: ISC License
Project-URL: Contributions, https://github.com/dnmellen/django-rest-friendship/graphs/contributors
Project-URL: Issues, https://github.com/dnmellen/django-rest-friendship/issues
Keywords: django,django-friendship,django-rest-friendship,friends,API,restframework,back-end,webdev,OOP
Platform: UNKNOWN
Classifier: Development Status :: 3 - Alpha
Classifier: Intended Audience :: Developers
Classifier: Topic :: Internet :: WWW/HTTP
Classifier: License :: OSI Approved :: ISC License (ISCL)
Classifier: Framework :: Django :: 3.2
Classifier: Framework :: Django :: 4.0
Classifier: Programming Language :: Python :: 3.8
Classifier: Programming Language :: Python :: 3.9
Classifier: Programming Language :: Python :: 3.10
Classifier: Operating System :: OS Independent
Classifier: Natural Language :: English
Classifier: Environment :: Web Environment
Requires-Python: <4,>=3.8
License-File: LICENSE
Requires-Dist: Django (>=3.2.9<5)
Requires-Dist: djangorestframework (==3.13.1)
Requires-Dist: django-friendship (>=1.9.4)
Provides-Extra: docs
Requires-Dist: mkdocs ; extra == 'docs'
Provides-Extra: test
Requires-Dist: coverage ; extra == 'test'
Requires-Dist: factory-boy ; extra == 'test'
Requires-Dist: flake8 ; extra == 'test'
Requires-Dist: pytest ; extra == 'test'
Requires-Dist: pytest-django ; extra == 'test'
Requires-Dist: tox ; extra == 'test'
